trace_reviewer/__init__.py
trace_reviewer/__main__.py
trace_reviewer/figpan.py
trace_reviewer/trace_manager.py
trace_reviewer/utilities.py
trace_reviewer-0.8.3.dist-info/LICENSE.txt
trace_reviewer-0.8.3.dist-info/METADATA
trace_reviewer-0.8.3.dist-info/WHEEL
trace_reviewer-0.8.3.dist-info/top_level.txt
trace_reviewer-0.8.3.dist-info/RECORD
