Metadata-Version: 2.1
Name: trace_reviewer
Version: 0.8.3
Summary: This is intended for reviewing and marking events occurring in intensity traces.
Author-email: Marcos Cervantes <mc2mn@virginia.edu>
Project-URL: repository, https://github.com/lambdacoffee/
Classifier: Programming Language :: Python :: 3
Classifier: Operating System :: OS Independent
Classifier: Development Status :: 4 - Beta
Requires-Python: >=3.6
License-File: LICENSE.txt
Requires-Dist: matplotlib >=3.4.2
Requires-Dist: numpy >=1.20.3
Requires-Dist: scikit-image >=0.19.3
Requires-Dist: scipy >=0.10.1
Requires-Dist: tqdm >=4.62.3
Requires-Dist: statsmodels >=0.13.1
Requires-Dist: imageio >=2.19.3
Requires-Dist: ruptures >=1.1.5
